setup.py
proccoli/__init__.py
proccoli.egg-info/PKG-INFO
proccoli.egg-info/SOURCES.txt
proccoli.egg-info/dependency_links.txt
proccoli.egg-info/requires.txt
proccoli.egg-info/top_level.txt