Metadata-Version: 1.0
Name: proccoli
Version: 0.1.1
Summary: Handy extensions for subprocess.Popen
Home-page: UNKNOWN
Author: Brian Lauber
Author-email: constructible.truth@gmail.com
License: UNKNOWN
Platform: UNKNOWN
